[
  {
    "title": "My Works",
    "description": "All about Haedal.",
    "url": "https://cafe.naver.com/haedaledu"
  },
  {
    "title": "My competition",
    "description": "Imagine Cup Junior.",
    "url": "https://www.youtube.com/watch?v=HUtUEOC5JH4"
  },
  {
    "title": "Scratch RPG",
    "description": "Gang.",
    "url": "https://www.youtube.com/watch?v=rNtNFF7Qfsk"
  },
  {
    "title": "GitHub Codespaces and github.dev",
    "description": "Video interview to explain when to use GitHub.dev versus GitHub Codespaces, and how best to use each tool.",
    "url": "https://www.youtube.com/watch?v=c3hHhRME_XI"
  }
]
